opl/__init__.py
opl/confluence.py
opl/constants.py
opl/incquery.py
opl/patterns.py
opl/sparql.py
opl/types.py
opl-1.0.10.dist-info/LICENSE
opl-1.0.10.dist-info/METADATA
opl-1.0.10.dist-info/WHEEL
opl-1.0.10.dist-info/top_level.txt
opl-1.0.10.dist-info/RECORD
